<CD-RAT><Entry><HWD>LF/PRES1</HWD><Activity><GapFillDragDrop layer="1" h="460" w="670" y="10" x="10" wordpool-position="above"><Title alignment="left" isOn="1">Past simple questions<br /></Title><Instruction alignment="left" isOn="1">Put the words into the correct order to make questions.<br /></Instruction><ReferenceObject soundIsOn="0" videoIsOn="0" defaultHeight="229" alignment="left" isOn="1"><Asset file="01112201.jpg" folder="images/" h="215" w="134" y="1" x="265" layer="1" type="graphic" /></ReferenceObject><ScrollableAssets /><Content><Question>1. <Gap><Score denom="4" num="1" />Where</Gap> <Gap><Score denom="4" num="1" />did</Gap> <Gap><Score denom="4" num="1" />they</Gap> <Gap><Score denom="4" num="1" />go on holiday?</Gap></Question><Question>2. <Gap><Score denom="4" num="1" />When</Gap> <Gap><Score denom="4" num="1" />did</Gap> <Gap><Score denom="4" num="1" />Carlos</Gap> <Gap><Score denom="4" num="1" />go to the mountains?</Gap></Question><Question>3. <Gap><Score denom="5" num="1" />What</Gap> <Gap><Score denom="5" num="1" />did</Gap> <Gap><Score denom="5" num="1" />she</Gap> <Gap><Score denom="5" num="1" />buy</Gap><br />    <Gap><Score denom="5" num="1" />at the shops?</Gap></Question><Question>4. <Gap><Score denom="4" num="1" />Did</Gap> <Gap><Score denom="4" num="1" />you</Gap> <Gap><Score denom="4" num="1" />go</Gap> <Gap><Score denom="4" num="1" />by bus?</Gap></Question><Question>5. <Gap><Score denom="3" num="1" />Were</Gap> <Gap><Score denom="3" num="1" />Frances and David</Gap> <Gap><Score denom="3" num="1" />at the hotel?</Gap></Question><Question>6. <Gap><Score denom="3" num="1" />Who</Gap> <Gap><Score denom="3" num="1" />did</Gap> <Gap><Score denom="3" num="1" />you go skiing with?</Gap></Question><Question>7. <Gap><Score denom="5" num="1" />Where</Gap> <Gap><Score denom="5" num="1" />did</Gap> <Gap><Score denom="5" num="1" />your family</Gap> <Gap><Score denom="5" num="1" />go</Gap><br />    <Gap><Score denom="5" num="1" />for a walk?</Gap></Question><Question>8. <Gap><Score denom="5" num="1" />When</Gap> <Gap><Score denom="5" num="1" />did</Gap> <Gap><Score denom="5" num="1" />you</Gap> <Gap><Score denom="5" num="1" />meet</Gap><br />    <Gap><Score denom="5" num="1" />Joao?</Gap></Question><Question>9. <Gap><Score denom="5" num="1" />What</Gap> <Gap><Score denom="5" num="1" />did</Gap> <Gap><Score denom="5" num="1" />Jo and Matt</Gap> <Gap><Score denom="5" num="1" />do</Gap>
<br />    <Gap><Score denom="5" num="1" />at the beach?</Gap></Question><Question>10. <Gap><Score denom="4" num="1" />Did</Gap> <Gap><Score denom="4" num="1" />the children</Gap> <Gap><Score denom="4" num="1" />go swimming</Gap> <Gap><Score denom="4" num="1" />this morning?</Gap></Question></Content></GapFillDragDrop><Feedback playallOn="1" showAnswersOn="1" animatedFeedbackOn="1" testModeOn="0" instantFeedbackOn="0"><Sounds /></Feedback><GenericActivity hintsNextTo="0" timerIsOn="0" CDPrefsFolder="xml/" CDPrefsFile="cd.xml"><ActivityCanvas graphicAlpha="100" folder="" file="" colourAlpha="100" colour="transparent" /><SoundLibrary y="10" x="10" isOn="0" /><VideoLibrary h="264.95" w="385" y="75.05" x="10" isOn="0" /><Assets /></GenericActivity></Activity></Entry></CD-RAT>