<CD-RAT><Entry><HWD>LF/PRES1</HWD><Activity><GapFillDropdown layer="1" h="420" w="670" y="10" x="10"><Title alignment="left" isOn="1">Time and tense<br /></Title><Instruction alignment="left" isOn="1">Choose the best answer to fit each gap.<br /></Instruction><ReferenceObject soundIsOn="0" videoIsOn="0" defaultHeight="203" alignment="left" isOn="1"><Asset file="06062101.jpg" folder="images/" h="189" w="130" y="0" x="271" layer="1" type="graphic" /></ReferenceObject><ScrollableAssets /><Content>1. It doesn’t matter where we <Dropdown default-text="Choose"><Score num="1" /><Choice>found</Choice><Choice>have found</Choice><Choice is-correct="1">find</Choice></Dropdown> to live as long as we’re near the countryside.<br />2. Peace talks <Dropdown default-text="Choose"><Score num="1" /><Choice>will be breaking down</Choice><Choice is-correct="1">break down</Choice><Choice>have broken down</Choice></Dropdown> within hours.<br />3. Keira Knightley <Dropdown default-text="Choose"><Score num="1" /><Choice>played</Choice><Choice is-correct="1">plays</Choice><Choice>has played</Choice></Dropdown> Elizabeth Bennett in this fantastic new film version of <br /><FONT COLOR="#FFFFFF">...</FONT><I>    Pride and Prejudice.</I><br />4. Snowstorms <Dropdown default-text="Choose"><Score num="1" /><Choice>will have forced</Choice><Choice is-correct="1">force</Choice><Choice>have been forcing</Choice></Dropdown> major airports to close.<br />5. Sharapova <Dropdown default-text="Choose"><Score num="1" /><Choice>will serve</Choice><Choice is-correct="1">serves</Choice><Choice>is serving</Choice></Dropdown> … and it’s an ace!!<br />6. And now I <Dropdown default-text="Choose"><Score num="1" /><Choice>walk</Choice><Choice is-correct="1">’m walking</Choice><Choice>walked</Choice></Dropdown> across the desert to try and find some form of wildlife.<br />7. A new production of <I>The Sound of Music</I> <Dropdown default-text="Choose"><Score num="1" /><Choice>opened</Choice><Choice is-correct="1">opens</Choice><Choice>has opened</Choice></Dropdown> in London next year.<br />8. I’ll move out as soon as I <Dropdown default-text="Choose"><Score num="1" /><Choice is-correct="1">find</Choice><Choice>will find</Choice><Choice>will have found</Choice></Dropdown> a new flat.<br />9. You can go home as soon as you <Dropdown default-text="Choose"><Score num="1" /><Choice>’re sorting</Choice><Choice is-correct="1">sort</Choice><Choice>will sort</Choice></Dropdown> out your office.<br />10. Jean and Fleur will have a fabulous time whether they <Dropdown default-text="Choose"><Score num="1" /><Choice>ski</Choice><Choice is-correct="1">’re skiing</Choice><Choice>’ll have been skiing</Choice></Dropdown> in Colorado or lying on<br /><FONT COLOR="#FFFFFF">.</FONT>     the beach in the Bahamas.</Content></GapFillDropdown><Feedback playallOn="1" showAnswersOn="1" animatedFeedbackOn="1" testModeOn="0" instantFeedbackOn="0"><Sounds /></Feedback><GenericActivity hintsNextTo="0" timerIsOn="0" CDPrefsFolder="xml/" CDPrefsFile="cd.xml"><ActivityCanvas graphicAlpha="100" folder="" file="" colourAlpha="100" colour="transparent" /><SoundLibrary y="10" x="10" isOn="0" /><VideoLibrary h="264.95" w="385" y="75.05" x="10" isOn="0" /><Assets /></GenericActivity></Activity></Entry></CD-RAT>