<CD-RAT><Entry><HWD>PRON</HWD><Activity><MultipleChoice layer="1" h="430" w="670" y="10" x="10"><Title alignment="left" isOn="1"><FONT FACE="Pelphon Pel SILDoulos"> / Æ: / / I / / FU /</FONT><br /></Title><Instruction alignment="left" isOn="1">Listen to the word and then choose the sound you hear.<br /></Instruction><ReferenceObject soundIsOn="0" videoIsOn="0" defaultHeight="200" alignment="left" isOn="0" /><ScrollableAssets /><Content><Question>1. th<U>ir</U>ty         <ReferenceObject><SoundFile endTime="0.81" startTime="0" duration="0.94" id="1" path="audio/06085101.mp3" /></ReferenceObject><Choices default-text="Choose   " is-dropdown="1"><Score num="1" /><Choice is-correct="1"><FONT FACE="Pelphon Pel SILDoulos"> / Æ: /</FONT><br /></Choice><Choice><FONT FACE="Pelphon Pel SILDoulos"> / I /</FONT><br /></Choice></Choices></Question><Question>2. r<U>o</U>mantic  <ReferenceObject><SoundFile endTime="1.1" startTime="0" duration="1.1" id="2" path="audio/06085102.mp3" /></ReferenceObject><Choices default-text="Choose   " is-dropdown="1"><Score num="1" /><Choice><FONT FACE="Pelphon Pel SILDoulos"> / I /</FONT></Choice><Choice is-correct="1"><FONT FACE="Pelphon Pel SILDoulos"> / FU /</FONT></Choice></Choices></Question><Question>3. im<U>a</U>ge      <ReferenceObject><SoundFile endTime="0.86" startTime="0" duration="0.86" id="3" path="audio/06085103.mp3" /></ReferenceObject><Choices default-text="Choose   " is-dropdown="1"><Score num="1" /><Choice is-correct="1"><FONT FACE="Pelphon Pel SILDoulos"> / I /</FONT></Choice><Choice><FONT FACE="Pelphon Pel SILDoulos"> / Æ: /</FONT></Choice></Choices></Question><Question>4. w<U>or</U>king    <ReferenceObject><SoundFile endTime="0.97" startTime="0" duration="0.97" id="4" path="audio/06085104.mp3" /></ReferenceObject><Choices default-text="Choose   " is-dropdown="1"><Score num="1" /><Choice><FONT FACE="Pelphon Pel SILDoulos"> / FU /</FONT></Choice><Choice is-correct="1"><FONT FACE="Pelphon Pel SILDoulos"> / Æ: /</FONT></Choice></Choices></Question><Question>5. wom<U>e</U>n     <ReferenceObject><SoundFile endTime="0.97" startTime="0" duration="0.97" id="5" path="audio/06085105.mp3" /></ReferenceObject><Choices default-text="Choose   " is-dropdown="1"><Score num="1" /><Choice is-correct="1"><FONT FACE="Pelphon Pel SILDoulos"> / I /</FONT></Choice><Choice><FONT FACE="Pelphon Pel SILDoulos"> / Æ: /</FONT></Choice></Choices></Question><Question>6.pers<U>o</U>na<ReferenceObject><SoundFile endTime="0.97" startTime="0" duration="0.97" id="6" path="audio/06085106.mp3" /></ReferenceObject><Choices default-text="Choose   " is-dropdown="1"><Score num="1" /><Choice is-correct="1"><FONT FACE="Pelphon Pel SILDoulos"> / FU /</FONT></Choice><Choice><FONT FACE="Pelphon Pel SILDoulos"> / I /</FONT></Choice></Choices></Question><Question>7. alm<U>o</U>st       <ReferenceObject><SoundFile endTime="1.05" startTime="0" duration="1.05" id="7" path="audio/06085107.mp3" /></ReferenceObject><Choices default-text="Choose   " is-dropdown="1"><Score num="1" /><Choice><FONT FACE="Pelphon Pel SILDoulos"> / I /</FONT></Choice><Choice is-correct="1"><FONT FACE="Pelphon Pel SILDoulos"> / FU /</FONT></Choice></Choices></Question><Question>8. p<U>e</U>rson<ReferenceObject><SoundFile endTime="0.97" startTime="0" duration="0.97" id="8" path="audio/06085108.mp3" /></ReferenceObject><Choices default-text="Choose   " is-dropdown="1"><Score num="1" /><Choice is-correct="1"><FONT FACE="Pelphon Pel SILDoulos"> / Æ: /</FONT></Choice><Choice><FONT FACE="Pelphon Pel SILDoulos"> / I /</FONT></Choice></Choices></Question><Question>9. beaut<U>i</U>ful     <ReferenceObject><SoundFile endTime="0.97" startTime="0" duration="0.97" id="9" path="audio/06085109.mp3" /></ReferenceObject><Choices default-text="Choose   " is-dropdown="1"><Score num="1" /><Choice is-correct="1"><FONT FACE="Pelphon Pel SILDoulos"> / I /</FONT></Choice><Choice><FONT FACE="Pelphon Pel SILDoulos"> / Æ: /</FONT></Choice></Choices></Question><Question>10. c<U>o</U>pe<ReferenceObject><SoundFile endTime="0.97" startTime="0" duration="0.97" id="10" path="audio/06085110.mp3" /></ReferenceObject><Choices default-text="Choose   " is-dropdown="1"><Score num="1" /><Choice><FONT FACE="Pelphon Pel SILDoulos"> / I /</FONT></Choice><Choice is-correct="1"><FONT FACE="Pelphon Pel SILDoulos"> / FU /</FONT></Choice></Choices></Question></Content></MultipleChoice><Feedback playallOn="1" showAnswersOn="1" animatedFeedbackOn="1" testModeOn="0" instantFeedbackOn="0"><Sounds /></Feedback><GenericActivity hintsNextTo="0" timerIsOn="0" CDPrefsFolder="xml/" CDPrefsFile="cd.xml"><ActivityCanvas graphicAlpha="100" folder="" file="" colourAlpha="100" colour="transparent" /><SoundLibrary y="10" x="10" isOn="0"><Item bDefault="1" endTime="0.81" startTime="0" duration="0.94" id="1" file="06085101.mp3" folder="audio/" /><Item endTime="1.1" startTime="0" duration="1.1" id="2" file="06085102.mp3" folder="audio/" /><Item endTime="0.86" startTime="0" duration="0.86" id="3" file="06085103.mp3" folder="audio/" /><Item endTime="0.97" startTime="0" duration="0.97" id="4" file="06085104.mp3" folder="audio/" /><Item endTime="0.97" startTime="0" duration="0.97" id="5" file="06085105.mp3" folder="audio/" /><Item endTime="0.97" startTime="0" duration="0.97" id="6" file="06085106.mp3" folder="audio/" /><Item endTime="1.05" startTime="0" duration="1.05" id="7" file="06085107.mp3" folder="audio/" /><Item endTime="0.97" startTime="0" duration="0.97" id="8" file="06085108.mp3" folder="audio/" /><Item endTime="0.97" startTime="0" duration="0.97" id="9" file="06085109.mp3" folder="audio/" /><Item endTime="0.97" startTime="0" duration="0.97" id="10" file="06085110.mp3" folder="audio/" /></SoundLibrary><VideoLibrary h="264.95" w="385" y="75.05" x="10" isOn="0" /><Assets /></GenericActivity></Activity></Entry></CD-RAT>