<CD-RAT><Entry><HWD>PRON</HWD><Activity><VoiceRecorder layer="1" h="460" w="600" y="10" x="10"><Title alignment="left" isOn="1">Past simple questions</Title><Instruction alignment="left" isOn="1">Click to listen to all the questions and answers, then record and playback part A.  <br /></Instruction><ReferenceObject soundPos="10,10" soundLayer="1" soundIsOn="1" videoIsOn="0" defaultHeight="272" alignment="left" isOn="0" /><ScrollableAssets /><Content><Question><Score num="1" /><ReferenceText2>1. A: Where did you go?</ReferenceText2><ListenButton2 id="1" url="" linkType="Sound" /><AudioRecorder /></Question><Question><Score num="1" /><ReferenceText1>    B: We went to Prague.</ReferenceText1><ListenButton id="2" url="" linkType="Sound" /></Question><Question><Score num="1" /><ReferenceText2>2. A: Who did you go with?</ReferenceText2><ListenButton2 id="3" url="" linkType="Sound" /><AudioRecorder /></Question><Question><Score num="1" /><ReferenceText1>    B: With my friend.</ReferenceText1><ListenButton id="4" url="" linkType="Sound" /></Question><Question><Score num="1" /><ReferenceText2>3. A: How did you get there?</ReferenceText2><ListenButton2 id="5" url="" linkType="Sound" /><AudioRecorder /></Question><Question><Score num="1" /><ReferenceText1>    B: By plane.</ReferenceText1><ListenButton id="6" url="" linkType="Sound" /></Question><Question><Score num="1" /><ReferenceText2>4. A: Why did you go there?</ReferenceText2><ListenButton2 id="7" url="" linkType="Sound" /><AudioRecorder /></Question><Question><Score num="1" /><ReferenceText1>    B: Because someone told us about it.</ReferenceText1><ListenButton id="8" url="" linkType="Sound" /></Question><Question><Score num="1" /><ReferenceText2>5. A: What did you think of it?</ReferenceText2><ListenButton2 id="9" url="" linkType="Sound" /><AudioRecorder /></Question><Question><Score num="1" /><ReferenceText1>    B: It was fantastic.</ReferenceText1><ListenButton id="10" url="" linkType="Sound" /></Question><Question><Score num="1" /><ReferenceText2>6. A: What did you do there?</ReferenceText2><ListenButton2 id="11" url="" linkType="Sound" /><AudioRecorder /></Question><Question><Score num="1" /><ReferenceText1>    B: We went to the old town, and to a club in the evening.</ReferenceText1><ListenButton id="12" url="" linkType="Sound" /></Question><Question><Score num="1" /><ReferenceText2>7. A: When did you come back?</ReferenceText2><ListenButton2 id="13" url="" linkType="Sound" /><AudioRecorder /></Question><Question><Score num="1" /><ReferenceText1>    B: Early this morning!</ReferenceText1><ListenButton id="14" url="" linkType="Sound" /></Question></Content></VoiceRecorder><Feedback playallOn="1" showAnswersOn="1" animatedFeedbackOn="1" testModeOn="0" instantFeedbackOn="0"><Sounds /></Feedback><GenericActivity hintsNextTo="0" timerIsOn="0" CDPrefsFolder="xml/" CDPrefsFile="cd.xml"><ActivityCanvas graphicAlpha="100" folder="" file="" colourAlpha="100" colour="transparent" /><SoundLibrary y="10" x="10" isOn="1"><Item bDefault="1" endTime="0.99" startTime="0" duration="0.99" id="1" file="02085201.mp3" folder="audio/" /><Item endTime="1.41" startTime="0" duration="1.41" id="2" file="02085202.mp3" folder="audio/" /><Item endTime="1.05" startTime="0" duration="1.05" id="3" file="02085203.mp3" folder="audio/" /><Item endTime="1.23" startTime="0" duration="1.23" id="4" file="02085204.mp3" folder="audio/" /><Item endTime="1.15" startTime="0" duration="1.15" id="5" file="02085205.mp3" folder="audio/" /><Item endTime="0.99" startTime="0" duration="0.99" id="6" file="02085206.mp3" folder="audio/" /><Item endTime="1.2" startTime="0" duration="1.2" id="7" file="02085207.mp3" folder="audio/" /><Item endTime="2.33" startTime="0" duration="2.33" id="8" file="02085208.mp3" folder="audio/" /><Item endTime="1.36" startTime="0" duration="1.36" id="9" file="02085209.mp3" folder="audio/" /><Item endTime="1.7" startTime="0" duration="1.7" id="10" file="02085210.mp3" folder="audio/" /><Item endTime="1.25" startTime="0" duration="1.25" id="11" file="02085211.mp3" folder="audio/" /><Item endTime="4.02" startTime="0" duration="4.02" id="12" file="02085212.mp3" folder="audio/" /><Item endTime="1.28" startTime="0" duration="1.28" id="13" file="02085213.mp3" folder="audio/" /><Item endTime="1.59" startTime="0" duration="1.59" id="14" file="02085214.mp3" folder="audio/" /></SoundLibrary><VideoLibrary h="252" w="385" y="78" x="10" isOn="0" /><Assets /></GenericActivity></Activity></Entry></CD-RAT>