<CD-RAT><Entry><HWD>VOCAB</HWD><Activity><LabelPicture layer="1" h="460" w="670" y="10" x="10" wordpool-position="left"><Title alignment="left" isOn="1">‘Survival&apos; objects<br /></Title><Instruction alignment="left" isOn="1">Drag a word from the word pool to the correct label in the picture.<br /></Instruction><ReferenceObject soundIsOn="0" videoIsOn="0" defaultHeight="200" alignment="left" isOn="0" /><ScrollableAssets /><Content><Question><ImageFile size="361,289" file="03123201.jpg" folder="images/" /><Label pointer-pos="36,136" label-pos="-77,2.95"><Score num="1" />batteries</Label><Label pointer-pos="36,230.95" label-pos="-102,290"><Score num="1" />blanket</Label><Label pointer-pos="112.95,180" label-pos="-108,156"><Score num="1" />compass</Label><Label pointer-pos="180.95,79" label-pos="50,-2"><Score num="1" />enrgy bar</Label><Label pointer-pos="279.95,168" label-pos="261,307"><Score num="1" />fishing rod</Label><Label pointer-pos="335.95,249.95" label-pos="272,279"><Score num="1" />insect repellent</Label><Label pointer-pos="42,87" label-pos="10,30"><Score num="1" />knife</Label><Label pointer-pos="314.95,114" label-pos="263,0"><Score num="1" />magnifying glass</Label><Label pointer-pos="240.95,263.95" label-pos="133,308"><Score num="1" />rope</Label><Label pointer-pos="188.95,261.95" label-pos="-3,321"><Score num="1" />sunscreen</Label><Label pointer-pos="235.95,51" label-pos="140,20"><Score num="1" />tent</Label><Label pointer-pos="336.95,143" label-pos="-99,104"><Score num="1" />toothbrush</Label><Label pointer-pos="179.95,209.95" label-pos="-97,185"><Score num="1" />torch</Label></Question></Content></LabelPicture><Feedback playallOn="1" showAnswersOn="1" animatedFeedbackOn="1" testModeOn="0" instantFeedbackOn="0"><Sounds /></Feedback><GenericActivity hintsNextTo="0" timerIsOn="0" CDPrefsFolder="XML/" CDPrefsFile="cd.xml"><ActivityCanvas graphicAlpha="100" folder="" file="" colourAlpha="100" colour="transparent" /><SoundLibrary y="10" x="10" isOn="0" /><VideoLibrary h="252" w="385" y="78" x="10" isOn="0" /><Assets /></GenericActivity></Activity></Entry></CD-RAT>