<CD-RAT><Entry><HWD>PRON</HWD><Activity><VoiceRecorder layer="1" h="460" w="670" y="10" x="10"><Title alignment="left" isOn="1">Contractions and weak forms, <I>will</I> and <I>would</I><br /></Title><Instruction alignment="left" isOn="1">Click to listen to the sentences, then record and playback. Pay attention to the short forms.<br /></Instruction><ReferenceObject soundIsOn="0" videoIsOn="0" defaultHeight="233" alignment="left" isOn="0" /><ScrollableAssets /><Content><Question><Score num="1" /><ReferenceText2>1. He'll be eighteen next week.</ReferenceText2><ListenButton2 id="1" url="" linkType="Sound" /><AudioRecorder /></Question><Question><Score num="1" /><ReferenceText2>2. I'd like to speak to the manager, please.</ReferenceText2><ListenButton2 id="2" url="" linkType="Sound" /><AudioRecorder /></Question><Question><Score num="1" /><ReferenceText2>3. We'd rather go on Wednesday.</ReferenceText2><ListenButton2 id="3" url="" linkType="Sound" /><AudioRecorder /></Question><Question><Score num="1" /><ReferenceText2>4. It'll be hot tomorrow.</ReferenceText2><ListenButton2 id="4" url="" linkType="Sound" /><AudioRecorder /></Question><Question><Score num="1" /><ReferenceText2>5. I won't be here next week.</ReferenceText2><ListenButton2 id="5" url="" linkType="Sound" /><AudioRecorder /></Question><Question><Score num="1" /><ReferenceText2>6. We'd like to book online.</ReferenceText2><ListenButton2 id="6" url="" linkType="Sound" /><AudioRecorder /></Question><Question><Score num="1" /><ReferenceText2>7. I'll be with you in half an hour.</ReferenceText2><ListenButton2 id="7" url="" linkType="Sound" /><AudioRecorder /></Question><Question><Score num="1" /><ReferenceText2>8. They won't be ready today.</ReferenceText2><ListenButton2 id="8" url="" linkType="Sound" /><AudioRecorder /></Question><Question><Score num="1" /><ReferenceText2>9. I'd rather go in August.</ReferenceText2><ListenButton2 id="9" url="" linkType="Sound" /><AudioRecorder /></Question><Question><Score num="1" /><ReferenceText2>10. We won't stay long.</ReferenceText2><ListenButton2 id="10" url="" linkType="Sound" /><AudioRecorder /></Question></Content></VoiceRecorder><Feedback playallOn="1" showAnswersOn="1" animatedFeedbackOn="1" testModeOn="0" instantFeedbackOn="0"><Sounds /></Feedback><GenericActivity hintsNextTo="0" timerIsOn="0" CDPrefsFolder="XML/" CDPrefsFile="cd.xml"><ActivityCanvas graphicAlpha="100" folder="" file="" colourAlpha="100" colour="transparent" /><SoundLibrary y="10" x="10" isOn="0"><Item bDefault="1" endTime="2.12" startTime="0" duration="2.12" id="1" file="03065201.mp3" folder="audio/" /><Item endTime="2.17" startTime="0" duration="2.17" id="2" file="03065202.mp3" folder="audio/" /><Item endTime="1.88" startTime="0" duration="1.88" id="3" file="03065203.mp3" folder="audio/" /><Item endTime="1.49" startTime="0" duration="1.49" id="4" file="03065204.mp3" folder="audio/" /><Item endTime="1.78" startTime="0" duration="1.78" id="5" file="03065205.mp3" folder="audio/" /><Item endTime="1.75" startTime="0" duration="1.75" id="6" file="03065206.mp3" folder="audio/" /><Item endTime="1.93" startTime="0" duration="1.93" id="7" file="03065207.mp3" folder="audio/" /><Item endTime="1.49" startTime="0" duration="1.49" id="8" file="03065208.mp3" folder="audio/" /><Item endTime="1.59" startTime="0" duration="1.59" id="9" file="03065209.mp3" folder="audio/" /><Item endTime="1.28" startTime="0" duration="1.28" id="10" file="03065210.mp3" folder="audio/" /></SoundLibrary><VideoLibrary h="252" w="385" y="78" x="10" isOn="0" /><Assets /></GenericActivity></Activity></Entry></CD-RAT>