<CD-RAT><Entry><HWD>REAL</HWD><Activity><VoiceRecorder layer="1" h="410" w="670" y="60" x="10"><Title alignment="left" isOn="0">The Title<br /></Title><Instruction alignment="left" isOn="0">My default rubric text<br /></Instruction><ReferenceObject soundIsOn="0" videoIsOn="0" defaultHeight="200" alignment="left" isOn="0" /><ScrollableAssets /><Content><Question><Score num="1" /><ReferenceText1><FONT FACE="Stone Informal">CONVERSATION 1.</FONT><br /><FONT FACE="Stone Informal">Rob: Hello. </FONT></ReferenceText1><ListenButton id="1" url="" linkType="Sound" /><ReferenceText2><FONT FACE="Stone Informal">Lisa: Hi! Hello!  </FONT></ReferenceText2><ListenButton2 id="2" url="" linkType="Sound" /><AudioRecorder /></Question><Question><Score num="1" /><ReferenceText1><FONT FACE="Stone Informal">Jane: Hi Lisa!</FONT></ReferenceText1><ListenButton id="3" url="" linkType="Sound" /><ReferenceText2><FONT FACE="Stone Informal">Lisa: Hi Jane. Lovely to see you! </FONT></ReferenceText2><ListenButton2 id="4" url="" linkType="Sound" /><AudioRecorder /></Question><Question><Score num="1" /><ReferenceText1><FONT FACE="Stone Informal">Jane: Happy birthday!!</FONT></ReferenceText1><ListenButton id="5" url="" linkType="Sound" /><ReferenceText2><FONT FACE="Stone Informal">Lisa: Oh, thank you.</FONT></ReferenceText2><ListenButton2 id="6" url="" linkType="Sound" /><AudioRecorder /></Question><Question><Score num="1" /><ReferenceText1><FONT FACE="Stone Informal">Rob: Oh, yeah ... Happy birthday … Many happy returns … these are for you …</FONT></ReferenceText1><ListenButton id="7" url="" linkType="Sound" /><ReferenceText2><FONT FACE="Stone Informal">Lisa: Oh thank you … they’re lovely …</FONT></ReferenceText2><ListenButton2 id="8" url="" linkType="Sound" /><AudioRecorder /></Question><Question><Score num="1" /><ReferenceText1><FONT FACE="Stone Informal">Jane: This is for you. I hope you like it.</FONT></ReferenceText1><ListenButton id="9" url="" linkType="Sound" /><ReferenceText2><FONT FACE="Stone Informal">Lisa: Oh, thank you. Well ... come through … let’s all have a drink … Nick, they’re here!!</FONT></ReferenceText2><ListenButton2 id="10" url="" linkType="Sound" /><AudioRecorder /></Question><Question><Score num="1" /><ReferenceText1><FONT FACE="Stone Informal">CONVERSATION 2.</FONT><br /><FONT FACE="Stone Informal">Rob: Mmm this is good.  Shall I tell them? Nick, Lisa … we’ve got some news ... Jane and I are ... going to </FONT><br /><FONT FACE="Stone Informal">        get married.</FONT></ReferenceText1><ListenButton id="11" url="" linkType="Sound" /></Question><Question><Score num="1" /><ReferenceText1><FONT FACE="Stone Informal">Lisa: No!!!</FONT></ReferenceText1><ListenButton id="12" url="" linkType="Sound" /><ReferenceText2><FONT FACE="Stone Informal">Nick: Wow!! Really?</FONT></ReferenceText2><ListenButton2 id="13" url="" linkType="Sound" /><AudioRecorder /></Question><Question><Score num="1" /><ReferenceText1><FONT FACE="Stone Informal">Jane: Yeah! It’s true! </FONT></ReferenceText1><ListenButton id="14" url="" linkType="Sound" /></Question><Question><Score num="1" /><ReferenceText1><FONT FACE="Stone Informal">Lisa: Oh that’s fantastic! Congratulations! </FONT></ReferenceText1><ListenButton id="15" url="" linkType="Sound" /><ReferenceText2><FONT FACE="Stone Informal">Nick: Yeah, brilliant!  Congratulations!  I hope you’ll be really happy.</FONT></ReferenceText2><ListenButton2 id="16" url="" linkType="Sound" /><AudioRecorder /></Question><Question><Score num="1" /><ReferenceText1><FONT FACE="Stone Informal">Rob: Thanks. I’m sure we will be. </FONT></ReferenceText1><ListenButton id="17" url="" linkType="Sound" /><ReferenceText2><FONT FACE="Stone Informal">Nick: Well, this really is a special occasion!  Cheers!  The best of luck for the future.  </FONT></ReferenceText2><ListenButton2 id="18" url="" linkType="Sound" /><AudioRecorder /></Question><Question><Score num="1" /><ReferenceText1><FONT FACE="Stone Informal">Rob, Jane, Lisa: Cheers!</FONT></ReferenceText1><ListenButton id="19" url="" linkType="Sound" /></Question></Content></VoiceRecorder><Feedback playallOn="1" showAnswersOn="1" animatedFeedbackOn="1" testModeOn="0" instantFeedbackOn="0"><Sounds /></Feedback><GenericActivity hintsNextTo="0" timerIsOn="0"><ActivityCanvas graphicAlpha="100" folder="" file="" colourAlpha="100" colour="transparent" /><SoundLibrary y="10" x="10" isOn="0"><Item bDefault="1" endTime="1.54" startTime="0" duration="1.54" id="1" file="Pre-Int0401.mp3" folder="video/audio/" /><Item endTime="1.86" startTime="0" duration="1.86" id="2" file="Pre-Int0402.mp3" folder="video/audio/" /><Item endTime="2.01" startTime="0" duration="2.01" id="3" file="Pre-Int0403.mp3" folder="video/audio/" /><Item endTime="2.61" startTime="0" duration="2.61" id="4" file="Pre-Int0404.mp3" folder="video/audio/" /><Item endTime="1.54" startTime="0" duration="1.54" id="5" file="Pre-Int0405.mp3" folder="video/audio/" /><Item endTime="1.86" startTime="0" duration="1.86" id="6" file="Pre-Int0406.mp3" folder="video/audio/" /><Item endTime="5.15" startTime="0" duration="5.15" id="7" file="Pre-Int0407.mp3" folder="video/audio/" /><Item endTime="4.83" startTime="0" duration="4.83" id="8" file="Pre-Int0408.mp3" folder="video/audio/" /><Item endTime="3.66" startTime="0" duration="3.66" id="9" file="Pre-Int0409.mp3" folder="video/audio/" /><Item endTime="11.7" startTime="0" duration="11.7" id="10" file="Pre-Int0410.mp3" folder="video/audio/" /><Item endTime="14.81" startTime="0" duration="14.81" id="11" file="Pre-Int0411.mp3" folder="video/audio/" /><Item endTime="2.01" startTime="0" duration="2.01" id="12" file="Pre-Int0412.mp3" folder="video/audio/" /><Item endTime="2.17" startTime="0" duration="2.17" id="13" file="Pre-Int0413.mp3" folder="video/audio/" /><Item endTime="1.86" startTime="0" duration="1.86" id="14" file="Pre-Int0414.mp3" folder="video/audio/" /><Item endTime="4.52" startTime="0" duration="4.52" id="15" file="Pre-Int0415.mp3" folder="video/audio/" /><Item endTime="4.99" startTime="0" duration="4.99" id="16" file="Pre-Int0416.mp3" folder="video/audio/" /><Item endTime="3.21" startTime="0" duration="3.21" id="17" file="Pre-Int0417.mp3" folder="video/audio/" /><Item endTime="5.43" startTime="0" duration="5.43" id="18" file="Pre-Int0418.mp3" folder="video/audio/" /><Item endTime="1.86" startTime="0" duration="1.86" id="19" file="Pre-Int0419.mp3" folder="video/audio/" /></SoundLibrary><VideoLibrary h="265.8" w="385" y="74.2" x="10" isOn="0" /><Assets /></GenericActivity></Activity></Entry></CD-RAT>